jwpure/__init__.py
jwpure/_version.py
jwpure/analyze.py
jwpure/query.py
jwpure/scripts.py
jwpure/data/pure_slots.csv
jwpure-1.0.0.dist-info/licenses/LICENSE
jwpure-1.0.0.dist-info/METADATA
jwpure-1.0.0.dist-info/WHEEL
jwpure-1.0.0.dist-info/top_level.txt
jwpure-1.0.0.dist-info/RECORD
