Metadata-Version: 2.4
Name: jwpure
Version: 1.0.0
Summary: Assess JWST pure parallel opportunities for specific observing requirements
Author: Jeff Valenti
Project-URL: repository, https://github.com/spacetelescope/jwst-pure-parallel
Project-URL: homepage, https://github.com/spacetelescope/jwst-pure-parallel
Project-URL: Tracker, https://github.com/spacetelescope/jwst-pure-parallel/issues
Classifier: Development Status :: 4 - Beta
Classifier: Programming Language :: Python :: 3
Classifier: Programming Language :: Python :: 3 :: Only
Classifier: Programming Language :: Python :: 3.11
Classifier: Programming Language :: Python :: 3.12
Classifier: Programming Language :: Python :: 3.13
Requires-Python: >=3.11
License-File: LICENSE
Requires-Dist: setuptools_scm
Requires-Dist: astropy
Requires-Dist: numpy>=2.0
Provides-Extra: tests
Requires-Dist: pytest; extra == "tests"
Requires-Dist: pytest-cov; extra == "tests"
Provides-Extra: linter
Requires-Dist: ruff; extra == "linter"
Dynamic: license-file
